delay/__init__.py
delay/api/__init__.py
delay/core/__init__.py
delay/core/delay_demo.py
delay/core/delay_essence.py
delay/core/echoes_essence.py
delay/core/knowledge_graph.py
delay/models/__init__.py
echo/__init__.py
echo/api/__init__.py
echo/core/__init__.py
echo/core/core.py
echo/core/knowledge.py
echo/core/knowledge_graph.py
echo/models/__init__.py
echo/models/items.py
reverb/__init__.py
reverb/__main__.py
reverb/demo.py
reverb/spatial_demo.py
reverb/api/__init__.py
reverb/core/__init__.py
reverb/core/platform.py
reverb/core/spatial_audio_visualizer.py
reverb/models/__init__.py
reverb/models/signal.py
reverb/services/__init__.py
reverb/services/delay_service.py
reverb/services/echo_service.py
reverb/services/reverb_service.py
reverb/services/spatial_service.py
routing/__init__.py
routing/acoustic_routing/__init__.py
routing/acoustic_routing/api/__init__.py
routing/acoustic_routing/api/routes.py
routing/acoustic_routing/core/__init__.py
routing/acoustic_routing/core/network.py
routing/acoustic_routing/core/visualization.py
routing/api/__init__.py
routing/core/__init__.py
routing/models/__init__.py
atmosphere-0.1.1.dist-info/METADATA
atmosphere-0.1.1.dist-info/WHEEL
atmosphere-0.1.1.dist-info/top_level.txt
atmosphere-0.1.1.dist-info/RECORD
