Metadata-Version: 2.4
Name: atmosphere
Version: 0.1.1
Summary: A comprehensive audio processing and routing system
Author-email: Your Name <your.email@example.com>
Project-URL: Homepage, https://github.com/yourusername/atmosphere
Classifier: Programming Language :: Python :: 3
Classifier: License :: OSI Approved :: MIT License
Classifier: Operating System :: OS Independent
Requires-Python: >=3.8
Provides-Extra: dev
Requires-Dist: pytest>=6.0; extra == "dev"
Requires-Dist: pytest-cov>=2.0; extra == "dev"
Requires-Dist: black>=21.7b0; extra == "dev"
Requires-Dist: isort>=5.0; extra == "dev"
Requires-Dist: mypy>=0.910; extra == "dev"
Requires-Dist: flake8>=3.9.0; extra == "dev"
